thedevilseye/__init__.py
thedevilseye/main.py
thedevilseye/thedevilseye.py
thedevilseye-2022.1.5.1.dist-info/LICENSE
thedevilseye-2022.1.5.1.dist-info/METADATA
thedevilseye-2022.1.5.1.dist-info/WHEEL
thedevilseye-2022.1.5.1.dist-info/entry_points.txt
thedevilseye-2022.1.5.1.dist-info/top_level.txt
thedevilseye-2022.1.5.1.dist-info/RECORD
