Metadata-Version: 2.1
Name: thedevilseye
Version: 2022.1.5.1
Summary: Darkweb osint tool
Home-page: https://github.com/rly0nheart/thedevilseye
Author: Richard Mwewa
Author-email: rly0nheart@duck.com
License: GNU General Public License v3 (GPLv3)
Classifier: Development Status :: 5 - Production/Stable
Classifier: Intended Audience :: Information Technology
Classifier: License :: OSI Approved :: GNU General Public License v3 (GPLv3)
Classifier: Operating System :: OS Independent
Classifier: Natural Language :: English
Classifier: Programming Language :: Python :: 3
License-File: LICENSE
Requires-Dist: rich
Requires-Dist: selenium
